README.rst
setup.py
django_validate_model_attribute_assignment/__init__.py
django_validate_model_attribute_assignment/models.py
django_validate_model_attribute_assignment.egg-info/PKG-INFO
django_validate_model_attribute_assignment.egg-info/SOURCES.txt
django_validate_model_attribute_assignment.egg-info/dependency_links.txt
django_validate_model_attribute_assignment.egg-info/requires.txt
django_validate_model_attribute_assignment.egg-info/top_level.txt