Metadata-Version: 1.0
Name: django-validate-model-attribute-assignment
Version: 2.0.2
Summary: Prevent typos and other errors when assigning attributes to Django model instances
Home-page: https://chris-lamb.co.uk/projects/django-validate-model-attribute-assignment
Author: Chris Lamb
Author-email: chris@chris-lamb.co.uk
License: BSD
Platform: UNKNOWN
